{"title":"Love and Honor (2013) 1080p x264 DD5.1 (External NL Subs)","uid":8186681,"size":1521462301,"categoryP":"video","categoryS":"hd___movies","magnet":"?xt=urn:btih:00831cc6743f82685f870ab8753da543ac3750f9&amp;dn=Love+and+Honor+%282013%29+1080p+x264+DD5.1+%28External+NL+Subs%29&amp;tr=udp%3A%2F%2Ftracker.openbittorrent.com%3A80&amp;tr=udp%3A%2F%2Fopen.demonii.com%3A1337&amp;tr=udp%3A%2F%2Ftracker.coppersurfer.tk%3A6969&amp;tr=udp%3A%2F%2Fexodus.desync.com%3A6969","seeders":5,"leechers":1,"uploader":"Brownsugar13","files":5,"time":1361738529,"description":"Love and Honor (2013) 1080p x264 DD5.1  (External NL Subs)\n &lt;a href=&quot;\nhttp://www.shotpix.com/images/48172932614398054999.jpg&quot; rel=&quot;nofollow&quot; target=&quot;_NEW&quot;&gt;\nhttp://www.shotpix.com/images/48172932614398054999.jpg&lt;/a&gt;\n\nFormat                       : Matroska\nFile size                    : 1.42 GiB\nDuration                     : 1h 35mn\nOverall bit rate             : 2 115 Kbps\n\nVideo\nFormat                       : AVC\nBit rate                     : 1 729 Kbps\nWidth                        : 1 920 pixels\nHeight                       : 816 pixels\n\nAudio\nID                           : 2\nFormat                       : AC-3\nBit rate mode                : Constant\nBit rate                     : 384 Kbps\nChannel(s)                   : 6 channels\nAudio                        : English\nSubtitle                     : Dutch,external srt file !\nEncoder                      : Brownsugar13,2-Pass\n\n\n\n\nQuality over Quantity (QoQ) Releases\nVertaling: r3p0 ~ Controle: pinkGaai,bedankt !\n\n\n\n\nscreenshots: &lt;a href=&quot;\nhttp://imageshack.us/a/img850/7411/vlcsnap2013022420h07m33.png&quot; rel=&quot;nofollow&quot; target=&quot;_NEW&quot;&gt;\nhttp://imageshack.us/a/img850/7411/vlcsnap2013022420h07m33.png&lt;/a&gt;\n &lt;a href=&quot;\nhttp://imageshack.us/a/img10/7513/vlcsnap2013022420h08m25.png&quot; rel=&quot;nofollow&quot; target=&quot;_NEW&quot;&gt;\nhttp://imageshack.us/a/img10/7513/vlcsnap2013022420h08m25.png&lt;/a&gt;\n &lt;a href=&quot;\nhttp://imageshack.us/a/img221/3560/vlcsnap2013022420h08m40.png&quot; rel=&quot;nofollow&quot; target=&quot;_NEW&quot;&gt;\nhttp://imageshack.us/a/img221/3560/vlcsnap2013022420h08m40.png&lt;/a&gt;\n &lt;a href=&quot;\nhttp://imageshack.us/a/img833/3080/vlcsnap2013022420h08m52.png&quot; rel=&quot;nofollow&quot; target=&quot;_NEW&quot;&gt;\nhttp://imageshack.us/a/img833/3080/vlcsnap2013022420h08m52.png&lt;/a&gt;\n\n\n\n &lt;a href=&quot;\nhttp://www.imdb.com/title/tt1976989/&quot; rel=&quot;nofollow&quot; target=&quot;_NEW&quot;&gt;\nhttp://www.imdb.com/title/tt1976989/&lt;/a&gt;\n &lt;a href=&quot;\nhttp://www.moviemeter.nl/film/85525&quot; rel=&quot;nofollow&quot; target=&quot;_NEW&quot;&gt;\nhttp://www.moviemeter.nl/film/85525&lt;/a&gt;","torrent":{"xt":"urn:btih:00831cc6743f82685f870ab8753da543ac3750f9","amp;dn":"Love+and+Honor+%282013%29+1080p+x264+DD5.1+%28External+NL+Subs%29","amp;tr":["udp%3A%2F%2Ftracker.openbittorrent.com%3A80","udp%3A%2F%2Fopen.demonii.com%3A1337","udp%3A%2F%2Ftracker.coppersurfer.tk%3A6969","udp%3A%2F%2Fexodus.desync.com%3A6969"],"infoHash":"00831cc6743f82685f870ab8753da543ac3750f9","infoHashBuffer":{"type":"Buffer","data":[0,131,28,198,116,63,130,104,95,135,10,184,117,61,165,67,172,55,80,249]},"announce":[],"urlList":[]}}