{"title":"Oliver Heldens - Heldeep Radio #050 (2015-05-17)","uid":11933322,"size":149556136,"categoryP":"audio","categoryS":"music","magnet":"?xt=urn:btih:0c46b87182dbbc274fcec25e76956957c18039a3&amp;dn=Oliver+Heldens+-+Heldeep+Radio+%23050+%282015-05-17%29&amp;tr=udp%3A%2F%2Ftracker.openbittorrent.com%3A80&amp;tr=udp%3A%2F%2Fopen.demonii.com%3A1337&amp;tr=udp%3A%2F%2Ftracker.coppersurfer.tk%3A6969&amp;tr=udp%3A%2F%2Fexodus.desync.com%3A6969","seeders":5,"leechers":0,"uploader":"ClubTime","files":22,"time":1431823298,"description":"Oliver Heldens - Heldeep Radio #050\nMixed By Oliver Heldens \nSplit Version\nGenres: Electro, House\nQuality: 320kbps/44khz/Stereo (MP3)\n\nWebsite of ClubTime: www.clubtime.se \nFacebook of ClubTime: /clubtimefp\nTwitter of ClubTime: /ClubTimeSE\nInstagram Of ClubTime: /clubtime.se/\n\nTracklist:\n01) The Ironix - Lost In The Water (USB Players Remix)\n02) Inpetto - Gravity (feat. Sean Declase) (Original Mix) (World Premiere)\n03) Curbi - Rubber (Original Mix)\n04) Oliver Heldens - Bunnydance (Original Mix)\n05) Motez - Tryna Shake It\n\nHeldeep Radio Cooldown\n06) Lika Morgan - Relax Dont Do It (Original Mix)\n07) Galantis - Peanut Butter Jelly\n08) MarllDexx - Hype (Original Mix)\n09) Nick Base - Vice City\n\nHeldeep Radio Classic\n10) Bob Sinclar - New New New (feat. Vybrate, Queen Ifrica, Makedah) (Avicii Meets Yellow Remix)\n\n11) Rektchordz - Roar (Original Mix)\n12) Sanchez Veerus Divine - Be Sure 2 Remember Me\n13) Mak, Pasteman - Oh Baby (Original Mix)\n14) Cause &amp; Affect - Get To The cHopper\n15) Aaron Jackson - Rotate\n16) Ephwurd &amp; Jauz - Rock The Party\n17) Zeds Dead - Hadouken (Valentino Khan Remix)\n18) Pendulum - The Spiral","torrent":{"xt":"urn:btih:0c46b87182dbbc274fcec25e76956957c18039a3","amp;dn":"Oliver+Heldens+-+Heldeep+Radio+%23050+%282015-05-17%29","amp;tr":["udp%3A%2F%2Ftracker.openbittorrent.com%3A80","udp%3A%2F%2Fopen.demonii.com%3A1337","udp%3A%2F%2Ftracker.coppersurfer.tk%3A6969","udp%3A%2F%2Fexodus.desync.com%3A6969"],"infoHash":"0c46b87182dbbc274fcec25e76956957c18039a3","infoHashBuffer":{"type":"Buffer","data":[12,70,184,113,130,219,188,39,79,206,194,94,118,149,105,87,193,128,57,163]},"announce":[],"urlList":[]}}