{"title":"Macklemore Ft. Wanz - ThriftShop [iTunes Rip] L3G3ND","uid":8374638,"size":7597639,"categoryP":"audio","categoryS":"music","magnet":"?xt=urn:btih:13b726bc3d2ada4c5da922560c33d079af8d64de&amp;dn=Macklemore+Ft.+Wanz+-+ThriftShop+%5BiTunes+Rip%5D+L3G3ND&amp;tr=udp%3A%2F%2Ftracker.openbittorrent.com%3A80&amp;tr=udp%3A%2F%2Fopen.demonii.com%3A1337&amp;tr=udp%3A%2F%2Ftracker.coppersurfer.tk%3A6969&amp;tr=udp%3A%2F%2Fexodus.desync.com%3A6969","seeders":5,"leechers":0,"uploader":"L3G3ND","files":1,"time":1366015145,"description":"Macklemore Ft. Wanz - ThriftShop [iTunes Rip] L3G3ND","torrent":{"xt":"urn:btih:13b726bc3d2ada4c5da922560c33d079af8d64de","amp;dn":"Macklemore+Ft.+Wanz+-+ThriftShop+%5BiTunes+Rip%5D+L3G3ND","amp;tr":["udp%3A%2F%2Ftracker.openbittorrent.com%3A80","udp%3A%2F%2Fopen.demonii.com%3A1337","udp%3A%2F%2Ftracker.coppersurfer.tk%3A6969","udp%3A%2F%2Fexodus.desync.com%3A6969"],"infoHash":"13b726bc3d2ada4c5da922560c33d079af8d64de","infoHashBuffer":{"type":"Buffer","data":[19,183,38,188,61,42,218,76,93,169,34,86,12,51,208,121,175,141,100,222]},"announce":[],"urlList":[]}}