{"title":"Ana Popovic, 4 Albums","uid":8151840,"size":449868808,"categoryP":"audio","categoryS":"music","magnet":"?xt=urn:btih:154e835d182f989208db2685ac0612565e04514a&amp;dn=Ana+Popovic%2C+4+Albums&amp;tr=udp%3A%2F%2Ftracker.openbittorrent.com%3A80&amp;tr=udp%3A%2F%2Fopen.demonii.com%3A1337&amp;tr=udp%3A%2F%2Ftracker.coppersurfer.tk%3A6969&amp;tr=udp%3A%2F%2Fexodus.desync.com%3A6969","seeders":5,"leechers":0,"uploader":"kchat13","files":48,"time":1361059168,"description":"Ana Popovic - 4 Albums\nFormat - MP3\n1998  Ana Popovic &amp; Hush Hometown 320 Kbps\n2007  The Queen of the Blues Guitar 320 Kbps\n2008  Jam Sessions with Paul Personne 320 Kbps\n2011  Unconditional 192 Kbps","torrent":{"xt":"urn:btih:154e835d182f989208db2685ac0612565e04514a","amp;dn":"Ana+Popovic%2C+4+Albums","amp;tr":["udp%3A%2F%2Ftracker.openbittorrent.com%3A80","udp%3A%2F%2Fopen.demonii.com%3A1337","udp%3A%2F%2Ftracker.coppersurfer.tk%3A6969","udp%3A%2F%2Fexodus.desync.com%3A6969"],"infoHash":"154e835d182f989208db2685ac0612565e04514a","infoHashBuffer":{"type":"Buffer","data":[21,78,131,93,24,47,152,146,8,219,38,133,172,6,18,86,94,4,81,74]},"announce":[],"urlList":[]}}