{"title":"[CBM] Campione! 1-13 Complete (Dual Audio) [BDRip-720p-8bit]","uid":9368332,"size":10302191033,"categoryP":"video","categoryS":"hd___tv_shows","magnet":"?xt=urn:btih:1705f4fd43a60e14c168c1da081a1bb36969dd00&amp;dn=%5BCBM%5D+Campione%21+1-13+Complete+%28Dual+Audio%29+%5BBDRip-720p-8bit%5D&amp;tr=udp%3A%2F%2Ftracker.openbittorrent.com%3A80&amp;tr=udp%3A%2F%2Fopen.demonii.com%3A1337&amp;tr=udp%3A%2F%2Ftracker.coppersurfer.tk%3A6969&amp;tr=udp%3A%2F%2Fexodus.desync.com%3A6969","seeders":5,"leechers":4,"uploader":"darkj6","files":-1,"time":1387473953,"description":" ______   _______  ______    ___   _      ___  --------|\n|      | |   _   ||    _ |  |   | | |    |   ||   |----|    \n|  _    ||  |_|  ||   | ||  |   |_| |    |   ||   |___ \n| | |   ||       ||   |_||_ |      _|    |   ||    _  |\n| |_|   ||       ||    __  ||     |_  ___|   ||   | | |\n|       ||   _   ||   |  | ||    _  ||       ||   |_| |\n|______| |__| |__||___|  |_||___| |_||_______||_______|\n\n\nSome people suddenly find religion, but for 16-year-old Kusanagi GoDo, it's that REALLY old time\nreligion that's found him! As the result of defeating the God of War in mortal combat, GoDo's stuck\nwith the unwanted position of Campione!, or God Slayer, whose duty is to fight Herectical Gods whenever\nthey try to muscle in on the local turf. Not only is this likely to make GoDo roadkill on the Highway to\nHeaven, it's also a job that comes with a lot of other problems. Like how to deal with the fact that his\n&quot;enhanced status&quot; is attracting a bevy of overly-worshippy female followers. After all, they're just there\nto aid him in his demi-godly duties, right? So why is it that their leader, the demonically manipulative\nsword-mistress Erica Brandelli, seems to have such a devilish interest in encouraging some VERY unorthodox activities?\n\n\n\nVIDEO\nVideo Source: BD-J\nVideo Codec: H.264/AVC\nVideo Resolution: 1280x720p HD (16:9)\nVideo FPS: 23.976\n\nAUDIO\nCodec: AAC-LC\nTrack 1: English: Stereo\nTrack 2: Japanese: Stereo\n\nSUBTITLES\nTrack 1: English Signs/Songs\nTrack 1: English Subtitles\n\n\n________________$$$$\n______________$$____$$\n______________$$____$$\n______________$$____$$\n______________$$____$$\n______________$$____$$\n__________$$$$$$____$$$$$$\n________$$____$$____$$____$$$$\n________$$____$$____$$____$$__$$\n$$$$$$__$$____$$____$$____$$____$$\n$$____$$$$________________$$____$$\n$$______$$______________________$$\n__$$____$$______________________$$\n___$$$__$$______________________$$\n____$$__________________________$$\n_____$$$________________________$$\n______$$______________________$$$\n_______$$$____________________$$\n________$$____________________$$\n_________$$$________________$$$\n__________$$________________$$\n__________$$$$$$$$$$$$$$$$$$$$","torrent":{"xt":"urn:btih:1705f4fd43a60e14c168c1da081a1bb36969dd00","amp;dn":"%5BCBM%5D+Campione%21+1-13+Complete+%28Dual+Audio%29+%5BBDRip-720p-8bit%5D","amp;tr":["udp%3A%2F%2Ftracker.openbittorrent.com%3A80","udp%3A%2F%2Fopen.demonii.com%3A1337","udp%3A%2F%2Ftracker.coppersurfer.tk%3A6969","udp%3A%2F%2Fexodus.desync.com%3A6969"],"infoHash":"1705f4fd43a60e14c168c1da081a1bb36969dd00","infoHashBuffer":{"type":"Buffer","data":[23,5,244,253,67,166,14,20,193,104,193,218,8,26,27,179,105,105,221,0]},"announce":[],"urlList":[]}}