{"title":"[Cen]  [MGQ-008] The spinning de pervert doctor Serizawa develop","uid":9246809,"size":851808613,"categoryP":"porn","categoryS":"movies","magnet":"?xt=urn:btih:302eef7bf7eaf9015bc3e8ee4e94502030be4780&amp;dn=%5BCen%5D++%5BMGQ-008%5D+The+spinning+de+pervert+doctor+Serizawa+develop&amp;tr=udp%3A%2F%2Ftracker.openbittorrent.com%3A80&amp;tr=udp%3A%2F%2Fopen.demonii.com%3A1337&amp;tr=udp%3A%2F%2Ftracker.coppersurfer.tk%3A6969&amp;tr=udp%3A%2F%2Fexodus.desync.com%3A6969","seeders":5,"leechers":1,"uploader":"KlixXxo","files":1,"time":1385390056,"description":"[Cen]  [MGQ-008]\nThe spinning de pervert doctor Serizawa develop obsessed with anal clinic Anal\n\n &lt;a href=&quot;\nhttp://www.244pix.com/viewer.php?file=vrs9vfwlzy1q.jpg&quot; rel=&quot;nofollow&quot; target=&quot;_NEW&quot;&gt;\nhttp://www.244pix.com/viewer.php?file=vrs9vfwlzy1q.jpg&lt;/a&gt;\n &lt;a href=&quot;\nhttp://www.244pix.com/viewer.php?file=31who4hzrpi2.jpg&quot; rel=&quot;nofollow&quot; target=&quot;_NEW&quot;&gt;\nhttp://www.244pix.com/viewer.php?file=31who4hzrpi2.jpg&lt;/a&gt;","torrent":{"xt":"urn:btih:302eef7bf7eaf9015bc3e8ee4e94502030be4780","amp;dn":"%5BCen%5D++%5BMGQ-008%5D+The+spinning+de+pervert+doctor+Serizawa+develop","amp;tr":["udp%3A%2F%2Ftracker.openbittorrent.com%3A80","udp%3A%2F%2Fopen.demonii.com%3A1337","udp%3A%2F%2Ftracker.coppersurfer.tk%3A6969","udp%3A%2F%2Fexodus.desync.com%3A6969"],"infoHash":"302eef7bf7eaf9015bc3e8ee4e94502030be4780","infoHashBuffer":{"type":"Buffer","data":[48,46,239,123,247,234,249,1,91,195,232,238,78,148,80,32,48,190,71,128]},"announce":[],"urlList":[]}}