{"title":"Caribbeancom 011814-525 Yuu Shinoda JAV UNCENSORED","uid":9504801,"size":2351251781,"categoryP":"porn","categoryS":"hd___movies","magnet":"?xt=urn:btih:3c5089af5891fe7b23e6b56c5372830a43abe086&amp;dn=Caribbeancom+011814-525+Yuu+Shinoda+JAV+UNCENSORED&amp;tr=udp%3A%2F%2Ftracker.openbittorrent.com%3A80&amp;tr=udp%3A%2F%2Fopen.demonii.com%3A1337&amp;tr=udp%3A%2F%2Ftracker.coppersurfer.tk%3A6969&amp;tr=udp%3A%2F%2Fexodus.desync.com%3A6969","seeders":5,"leechers":0,"uploader":"3xplanet","files":1,"time":1390297343,"description":"Caribbeancom 011814-525 Yuu Shinoda JAV UNCENSORED\nCover &lt;a href=&quot;\nhttp://www.3xplanet.com/view/25658.html&quot; rel=&quot;nofollow&quot; target=&quot;_NEW&quot;&gt;\nhttp://www.3xplanet.com/view/25658.html&lt;/a&gt;\nScreenshot &lt;a href=&quot;\nhttp://www.3xplanet.com/view/25711.html&quot; rel=&quot;nofollow&quot; target=&quot;_NEW&quot;&gt;\nhttp://www.3xplanet.com/view/25711.html&lt;/a&gt;\nTitle: \nStarring: Yuu Shinoda\nStudio:  Caribbeancom\n\nTag: JAV, UNCENSORED, Caribbeancom, vibe, nice ass, handjob, debut, cunnilingus, cum inside, Creampie, blowjob, blowjob, Big tits\n\n","torrent":{"xt":"urn:btih:3c5089af5891fe7b23e6b56c5372830a43abe086","amp;dn":"Caribbeancom+011814-525+Yuu+Shinoda+JAV+UNCENSORED","amp;tr":["udp%3A%2F%2Ftracker.openbittorrent.com%3A80","udp%3A%2F%2Fopen.demonii.com%3A1337","udp%3A%2F%2Ftracker.coppersurfer.tk%3A6969","udp%3A%2F%2Fexodus.desync.com%3A6969"],"infoHash":"3c5089af5891fe7b23e6b56c5372830a43abe086","infoHashBuffer":{"type":"Buffer","data":[60,80,137,175,88,145,254,123,35,230,181,108,83,114,131,10,67,171,224,134]},"announce":[],"urlList":[]}}