{"title":"Taking Up Space + She Had it Coming 1 and 2 by TheAmericanDream","uid":11695631,"size":103343361,"categoryP":"other","categoryS":"other","magnet":"?xt=urn:btih:5accade220c381753f9f813ac8efef1c44f3696d&amp;dn=Taking+Up+Space+%2B+She+Had+it+Coming+1+and+2+by+TheAmericanDream&amp;tr=udp%3A%2F%2Ftracker.openbittorrent.com%3A80&amp;tr=udp%3A%2F%2Fopen.demonii.com%3A1337&amp;tr=udp%3A%2F%2Ftracker.coppersurfer.tk%3A6969&amp;tr=udp%3A%2F%2Fexodus.desync.com%3A6969","seeders":5,"leechers":0,"uploader":"N-Kush","files":93,"time":1423695319,"description":"Three comics:\nTaking up Space\nShe Had it Coming\nShe Had it Coming II\n\nfor people on the internet obsessed with women who have...additional assets","torrent":{"xt":"urn:btih:5accade220c381753f9f813ac8efef1c44f3696d","amp;dn":"Taking+Up+Space+%2B+She+Had+it+Coming+1+and+2+by+TheAmericanDream","amp;tr":["udp%3A%2F%2Ftracker.openbittorrent.com%3A80","udp%3A%2F%2Fopen.demonii.com%3A1337","udp%3A%2F%2Ftracker.coppersurfer.tk%3A6969","udp%3A%2F%2Fexodus.desync.com%3A6969"],"infoHash":"5accade220c381753f9f813ac8efef1c44f3696d","infoHashBuffer":{"type":"Buffer","data":[90,204,173,226,32,195,129,117,63,159,129,58,200,239,239,28,68,243,105,109]},"announce":[],"urlList":[]}}