{"title":"Ty Segall Melted Gone 58 Stereo FLAC","uid":6016939,"size":211288404,"categoryP":"audio","categoryS":"flac","magnet":"?xt=urn:btih:62a744cf84471bbe3ed069242cbb3f553a63a08d&amp;dn=Ty+Segall+Melted+Gone+58+Stereo+FLAC&amp;tr=udp%3A%2F%2Ftracker.openbittorrent.com%3A80&amp;tr=udp%3A%2F%2Fopen.demonii.com%3A1337&amp;tr=udp%3A%2F%2Ftracker.coppersurfer.tk%3A6969&amp;tr=udp%3A%2F%2Fexodus.desync.com%3A6969","seeders":5,"leechers":1,"uploader":"staxlightninvolt","files":12,"time":1291663379,"description":"FOLDER INFO\n\nARTIST-TY SEGALL \nALBUM-MELTED\nAUDIO-STEREOPHONIC \nCATALOG NUMBER-GONE 58 \n\n\n\nNERD INFO\n\nSOURCE-MP3 TO FLAC\nAPPLICATIONS-LAME&gt;FRONT END\n932 KB/S\n2 CHANNEL\n44100 SAMPLE RATE\n\n\nIF YOU NEED THIS AS VINYL RIP OR ANY OTHER VINYL RIPS PLEASE CONTACT ME \nI DIDN'T HAVE TIME TO SAMPLE THE VINYL AS I DO THIS ALL DAY FOR A LIVING!\n\nI HAVE OVER 15,000 LPS AND 45'S 78'S PLEASE LET ME KNOW.\n\n&lt;a class=&quot;__cf_email__&quot; href=&quot;/cdn-cgi/l/email-protection&quot; data-cfemail=&quot;a3eee6e3f7ebe6efe2ede7ece5e292939393e7e2ede0e6f08de0ecee&quot;&gt;[email&amp;#160;protected]&lt;/a&gt;&lt;script cf-hash='f9e31' type=&quot;text/javascript&quot;&gt;\n/* &lt;![CDATA[ */!function(){try{var t=&quot;currentScript&quot;in document?document.currentScript:function(){for(var t=document.getElementsByTagName(&quot;script&quot;),e=t.length;e--;)if(t[e].getAttribute(&quot;cf-hash&quot;))return t[e]}();if(t&amp;&amp;t.previousSibling){var e,r,n,i,c=t.previousSibling,a=c.getAttribute(&quot;data-cfemail&quot;);if(a){for(e=&quot;&quot;,r=parseInt(a.substr(0,2),16),n=2;a.length-n;n+=2)i=parseInt(a.substr(n,2),16)^r,e+=String.fromCharCode(i);e=document.createTextNode(e),c.parentNode.replaceChild(e,c)}}}catch(u){}}();/* ]]&gt; */&lt;/script&gt;\n\nWE ARE NOT TAKING ANYONES ARTISITC OR INTELLECTUAL PROPERTY AND EXPLOIITNG IT. WE ARE SIMPLY PROVIDING CONNISUERS WITH HIGH END AUDIOPHILE QUALITY FILES OF THEIR FAVORITE ALBUM OR ARTISTS!\n\nUNTIL THEY DO...\n\nCHEERS AND COMMENT IF YOU LIKE!","torrent":{"xt":"urn:btih:62a744cf84471bbe3ed069242cbb3f553a63a08d","amp;dn":"Ty+Segall+Melted+Gone+58+Stereo+FLAC","amp;tr":["udp%3A%2F%2Ftracker.openbittorrent.com%3A80","udp%3A%2F%2Fopen.demonii.com%3A1337","udp%3A%2F%2Ftracker.coppersurfer.tk%3A6969","udp%3A%2F%2Fexodus.desync.com%3A6969"],"infoHash":"62a744cf84471bbe3ed069242cbb3f553a63a08d","infoHashBuffer":{"type":"Buffer","data":[98,167,68,207,132,71,27,190,62,208,105,36,44,187,63,85,58,99,160,141]},"announce":[],"urlList":[]}}