{"title":"[Chaturbate]Clava - Amateur  [.mp4]","uid":16037394,"size":801006252,"categoryP":"porn","categoryS":"movie_clips","magnet":"?xt=urn:btih:6a5a2ce2fa809a029ac7c3a4d2b543a32c1e2caf&amp;dn=%5BChaturbate%5DClava+-+Amateur++%5B.mp4%5D&amp;tr=udp%3A%2F%2Ftracker.leechers-paradise.org%3A6969&amp;tr=udp%3A%2F%2Fzer0day.ch%3A1337&amp;tr=udp%3A%2F%2Fopen.demonii.com%3A1337&amp;tr=udp%3A%2F%2Ftracker.coppersurfer.tk%3A6969&amp;tr=udp%3A%2F%2Fexodus.desync.com%3A6969","seeders":5,"leechers":3,"uploader":"TKTh3K1ng","files":1,"time":1476490839,"description":"Screenshots:\n \nhttp://tk.imgsking.com/img-58015a301ae4a.html","torrent":{"xt":"urn:btih:6a5a2ce2fa809a029ac7c3a4d2b543a32c1e2caf","amp;dn":"%5BChaturbate%5DClava+-+Amateur++%5B.mp4%5D","amp;tr":["udp%3A%2F%2Ftracker.leechers-paradise.org%3A6969","udp%3A%2F%2Fzer0day.ch%3A1337","udp%3A%2F%2Fopen.demonii.com%3A1337","udp%3A%2F%2Ftracker.coppersurfer.tk%3A6969","udp%3A%2F%2Fexodus.desync.com%3A6969"],"infoHash":"6a5a2ce2fa809a029ac7c3a4d2b543a32c1e2caf","infoHashBuffer":{"type":"Buffer","data":[106,90,44,226,250,128,154,2,154,199,195,164,210,181,67,163,44,30,44,175]},"announce":[],"urlList":[]}}