{"title":"Qualitycontrol.cc-----Visit with a special nurse Molly,Jen.wmv","uid":9843983,"size":70042211,"categoryP":"porn","categoryS":"movie_clips","magnet":"?xt=urn:btih:6b4de7d8b2c83f2dc3d1f472129104d69641f46e&amp;dn=Qualitycontrol.cc%5C-----Visit+with+a+special+nurse+Molly%2CJen.wmv&amp;tr=udp%3A%2F%2Ftracker.openbittorrent.com%3A80&amp;tr=udp%3A%2F%2Fopen.demonii.com%3A1337&amp;tr=udp%3A%2F%2Ftracker.coppersurfer.tk%3A6969&amp;tr=udp%3A%2F%2Fexodus.desync.com%3A6969","seeders":5,"leechers":0,"uploader":"merzedes","files":-1,"time":1396041626,"description":"Qualitycontrol.cc  Visit with a special nurse Molly,Jen.wmv\n\n\nScreens\n                                     &lt;a href=&quot;\nhttp://image.bayimg.com/c853bfb9eca23e8917c58679b91512c50361fd84.jpg&quot; rel=&quot;nofollow&quot; target=&quot;_NEW&quot;&gt;\nhttp://image.bayimg.com/c853bfb9eca23e8917c58679b91512c50361fd84.jpg&lt;/a&gt;\n\n                \n\n13 000 uploads and counting, 14k here we come :) And as usual, if you still like what Shallow2 and I upload, how about leaving us a nice comment below ? :)\n\n\nAny Questions ?? Read our FAQ!!\n                                                                                                                 &lt;a href=&quot;\nhttp://image.bayimg.com/eaea7e9e982a9a677d61e4f5aaf93b7643bd6eeb.jpg&quot; rel=&quot;nofollow&quot; target=&quot;_NEW&quot;&gt;\nhttp://image.bayimg.com/eaea7e9e982a9a677d61e4f5aaf93b7643bd6eeb.jpg&lt;/a&gt;\n\n\nCheers  :-)","torrent":{"xt":"urn:btih:6b4de7d8b2c83f2dc3d1f472129104d69641f46e","amp;dn":"Qualitycontrol.cc%5C-----Visit+with+a+special+nurse+Molly%2CJen.wmv","amp;tr":["udp%3A%2F%2Ftracker.openbittorrent.com%3A80","udp%3A%2F%2Fopen.demonii.com%3A1337","udp%3A%2F%2Ftracker.coppersurfer.tk%3A6969","udp%3A%2F%2Fexodus.desync.com%3A6969"],"infoHash":"6b4de7d8b2c83f2dc3d1f472129104d69641f46e","infoHashBuffer":{"type":"Buffer","data":[107,77,231,216,178,200,63,45,195,209,244,114,18,145,4,214,150,65,244,110]},"announce":[],"urlList":[]}}