{"title":"Teen Pies - Rachel Rose (Youve Been Extra Naughty)","uid":11672701,"size":374554588,"categoryP":"porn","categoryS":"movie_clips","magnet":"?xt=urn:btih:7114e98694f56e584ecaa4496f967ae622380a7a&amp;dn=Teen+Pies+-+Rachel+Rose+%28Youve+Been+Extra+Naughty%29&amp;tr=udp%3A%2F%2Ftracker.openbittorrent.com%3A80&amp;tr=udp%3A%2F%2Fopen.demonii.com%3A1337&amp;tr=udp%3A%2F%2Ftracker.coppersurfer.tk%3A6969&amp;tr=udp%3A%2F%2Fexodus.desync.com%3A6969","seeders":5,"leechers":1,"uploader":"Upl0ad3rR","files":1,"time":1422736663,"description":"---:More From My Torrent's Here:---  &lt;a href=&quot;\nhttps://thepiratebay.se/user/Upl0ad3rR&quot; rel=&quot;nofollow&quot; target=&quot;_NEW&quot;&gt;\nhttps://thepiratebay.se/user/Upl0ad3rR&lt;/a&gt;\n\n---:ScreeNshotS:---  &lt;a href=&quot;\nhttp://image-tpb.com/img-54cd2f044e6e9.html&quot; rel=&quot;nofollow&quot; target=&quot;_NEW&quot;&gt;\nhttp://image-tpb.com/img-54cd2f044e6e9.html&lt;/a&gt;  &lt;a href=&quot;\nhttp://image-tpb.com/img-54cd2f04bab7b.html&quot; rel=&quot;nofollow&quot; target=&quot;_NEW&quot;&gt;\nhttp://image-tpb.com/img-54cd2f04bab7b.html&lt;/a&gt; \n\nRachel was sleeping quiet as a mouse, when she heard a stirring from within her house. She shot up and wondered, What noise was that? When she saw Santa in her house with his sack! She spied from a distance in her lingerie as Santa noticed the milk and cookies on a tray. He took the bait and the trap was set - and this is when Rachel started to get wet. She dropped to her knees begging Santa for a gift and as an incentive she sucked on his dick! She couldnt stop there, Old Saint Nick wanted more so he took his rock hard cock and shoved it deep in that whore! With each thrust and each lick he felt the end coming near and he thought, Why dont I do this every year? Rachel was moaning loudly sprawled out on her back and this helped Santa empty his second sack! With one final push and a big HO HO HO Rachels tight pussy got Santa to blow. As his jizz dribbled out, and with a gleam in his eye - he turned to Rachel and said, See you next Yuletide!","torrent":{"xt":"urn:btih:7114e98694f56e584ecaa4496f967ae622380a7a","amp;dn":"Teen+Pies+-+Rachel+Rose+%28Youve+Been+Extra+Naughty%29","amp;tr":["udp%3A%2F%2Ftracker.openbittorrent.com%3A80","udp%3A%2F%2Fopen.demonii.com%3A1337","udp%3A%2F%2Ftracker.coppersurfer.tk%3A6969","udp%3A%2F%2Fexodus.desync.com%3A6969"],"infoHash":"7114e98694f56e584ecaa4496f967ae622380a7a","infoHashBuffer":{"type":"Buffer","data":[113,20,233,134,148,245,110,88,78,202,164,73,111,150,122,230,34,56,10,122]},"announce":[],"urlList":[]}}