{"title":"Rare Hits of The 80s Vol. 18","uid":3986223,"size":158555076,"categoryP":"audio","categoryS":"music","magnet":"?xt=urn:btih:7d662ba3afebd010cb3bf4a614b8e6859dd359f2&amp;dn=Rare+Hits+of+The+80s+Vol.+18&amp;tr=udp%3A%2F%2Ftracker.openbittorrent.com%3A80&amp;tr=udp%3A%2F%2Fopen.demonii.com%3A1337&amp;tr=udp%3A%2F%2Ftracker.coppersurfer.tk%3A6969&amp;tr=udp%3A%2F%2Fexodus.desync.com%3A6969","seeders":5,"leechers":0,"uploader":"80zforever","files":25,"time":1200829040,"description":"Rare Hits of The 80s Vol. 18. A compilation of rare new wave, minimal, synthpop and sophistipop songs. Enjoy and keep seeding!\n\nTracklisting:\n\n01 Pete Shelley - Waiting For Love\n02 Big Bam Boo - If You Could See Me Now\n03 The Quick - It&amp;#039;s An International Thing\n04 D.I.A. - Passion Play\n05 Stabilizers - One Simple Thing\n06 The Game - Walk Away\n07 Flaming Mussolinis - My Cleopatra\n08 Crown Of Thorns - Pictures\n09 Few Boys - Secret Times\n10 Click Click - She Can\n11 David Austin - Turn To Gold\n12 Sideway Look - Unlock the capital\n13 Neon Judgement - Awful Day\n14 No Time For Heroes - Dreams In The Night\n15 The Spoons - Romantic Traffic\n16 Catholic Girls - Boys Can Cry\n17 Sons Of Heroes - Living Outside Your Love\n18 The Names - Calcutta\n19 Balaam and the Angel - Two into One\n20 John Foxx - Noone Driving\n21 Walk on Water - Call My Name\n22 Bollock Brothers - Enchantment\n23 The Tenants - Sheriff\n24 The Raincoats - Love A Loser\n25 Robert King - Paper Heart","torrent":{"xt":"urn:btih:7d662ba3afebd010cb3bf4a614b8e6859dd359f2","amp;dn":"Rare+Hits+of+The+80s+Vol.+18","amp;tr":["udp%3A%2F%2Ftracker.openbittorrent.com%3A80","udp%3A%2F%2Fopen.demonii.com%3A1337","udp%3A%2F%2Ftracker.coppersurfer.tk%3A6969","udp%3A%2F%2Fexodus.desync.com%3A6969"],"infoHash":"7d662ba3afebd010cb3bf4a614b8e6859dd359f2","infoHashBuffer":{"type":"Buffer","data":[125,102,43,163,175,235,208,16,203,59,244,166,20,184,230,133,157,211,89,242]},"announce":[],"urlList":[]}}