{"title":"Drunk.History.S02E08.Philadelphia.720p.WEBRip.x264.AAC","uid":10752268,"size":363983315,"categoryP":"video","categoryS":"hd___tv_shows","magnet":"?xt=urn:btih:91f553eaf539c62d6a32624dadd8633ec37dcc52&amp;dn=Drunk.History.S02E08.Philadelphia.720p.WEBRip.x264.AAC&amp;tr=udp%3A%2F%2Ftracker.openbittorrent.com%3A80&amp;tr=udp%3A%2F%2Fopen.demonii.com%3A1337&amp;tr=udp%3A%2F%2Ftracker.coppersurfer.tk%3A6969&amp;tr=udp%3A%2F%2Fexodus.desync.com%3A6969","seeders":5,"leechers":0,"uploader":"loadstone2k12","files":-1,"time":1407886335,"description":"Drunk History - Season 2 - Episode 8 (WEBRip - 720p - MP4)\n----------------------------------------------------------\n\nOrder up another round of the smashed hit series! In season two,\nmore big name celebrities reenact the stories of famous (and\ninfamous) Americans -- from Benedict Arnold to Johnny Cash --\nas told by seriously wasted and totally confused comedians.\n\nProduced by Comedy Central.\n\n\nBaron von Steuben helps train the Continental Army during the American Revolution;\nJohn Adams and Thomas Jefferson campaign for president;\nBenedict Arnold switches sides to fight against George Washington's army.\n\nGuest Cast: Chris Parnell, Winona Ryder, David Cross and Stephen Merchant.\n\nDrunk.History.S02E08.Philadelphia.720p.WEBRip.x264.AAC.mp4\n\nVideo: MPEG4 Video (H264) 1280x720 23.976fps [CRF 20.0 - PS3 Preset]\nAudio: MPEG4 Audio (AAC) 48000Hz stereo  [128Kbps ABR]\nDuration: 00:21:15\nFile size: 347 MB\n\n\n* Closed Captions not online yet.\n","torrent":{"xt":"urn:btih:91f553eaf539c62d6a32624dadd8633ec37dcc52","amp;dn":"Drunk.History.S02E08.Philadelphia.720p.WEBRip.x264.AAC","amp;tr":["udp%3A%2F%2Ftracker.openbittorrent.com%3A80","udp%3A%2F%2Fopen.demonii.com%3A1337","udp%3A%2F%2Ftracker.coppersurfer.tk%3A6969","udp%3A%2F%2Fexodus.desync.com%3A6969"],"infoHash":"91f553eaf539c62d6a32624dadd8633ec37dcc52","infoHashBuffer":{"type":"Buffer","data":[145,245,83,234,245,57,198,45,106,50,98,77,173,216,99,62,195,125,204,82]},"announce":[],"urlList":[]}}