{"title":"Showdown.in.Manila.2016.1080p.WEBRip.AAC.x264-ETRG","uid":13959543,"size":2266613329,"categoryP":"video","categoryS":"hd___movies","magnet":"?xt=urn:btih:a83bc1a1016163011219df23377b6de06f77ed5f&amp;dn=Showdown.in.Manila.2016.1080p.WEBRip.AAC.x264-ETRG&amp;tr=udp%3A%2F%2Ftracker.leechers-paradise.org%3A6969&amp;tr=udp%3A%2F%2Fzer0day.ch%3A1337&amp;tr=udp%3A%2F%2Fopen.demonii.com%3A1337&amp;tr=udp%3A%2F%2Ftracker.coppersurfer.tk%3A6969&amp;tr=udp%3A%2F%2Fexodus.desync.com%3A6969","seeders":5,"leechers":6,"uploader":"tomcat-12","files":10,"time":1458571302,"description":"Showdown.in.Manila.2016.1080p.WEBRip.AAC.x264-ETRG\r\n\r\n\r\nplot\r\n\r\n\r\nThe film will unfold in Manila, Philippines, and in the jungles of the island of Boracay. On a tropical island in the privacy of living Russian middle-aged man (Alexander Newsky). But the quiet life interrupted by the murder of one of the locals. In order to protect the daughter of the slain Filipino bandits Russian guy have to remember the past, he tried to bury .\r\n\r\ncast\r\n\r\nAlexander Nevsky:...Nick Peyton\r\nCasper Van Dien:...Charlie\r\nCary-Hiroyuki Tagawa:...Aldric Cole\r\nMark Dacascos:...Matthew Wells\r\nTia Carrere:...Mrs. Wells\r\nMatthias Hues:...Dorn\r\n\r\n\r\n\r\nVideo:-\r\n\r\nFormat :mp4/AVC \r\nWriting Library :x264    \r\nDuration : 1h 25mn 57s \r\nBitrate : 3 300 Kbps   \r\nResolution=Width/Height : 1 920  x  1 010 pixels \r\nFrame Rate : 25.000 fps\r\n\r\nAudio:-\r\n\r\nFormat : AAC \r\nBitrate :  158 Kbps\r\nChannels : 2 Channels\r\nChannel Positions : Front: L - R \r\nSample Rate : 48KHz\r\nLanguage : English\r\n\r\nRelease info:-\r\n\r\nEncoded/Released By :tomcat12/ETRG \r\nTitle/Year : &quot;Showdown in Manila&quot; / 2016\r\nFile Size : 2.08 GiB  \r\nGenre : Action  \r\nSource : 1080p WEB-DL - HDCLUB [Thanks]\r\nChapters : Yes \r\nSample : Yes \r\nSubtitles: -.\r\nIMDB :   http://www.imdb.com/title/tt4586626/\r\n\r\n \nhttp://extraimago.com/image/a7AD \nhttp://extraimago.com/image/a7AF \nhttp://extraimago.com/image/a7AH \nhttp://extraimago.com/image/a7Ak \nhttp://extraimago.com/image/a7At \nhttp://extraimago.com/image/a7Ax\r\n     \r\n\r\nGreetz To: SaM |ozi|juggs|LRS|SureNdrA|Psix|Masta|MgB|Hand_of_Doom|BADASSMEDIA|FWOLF|Extratorrent|.\r\n\r\n\r\nMake sure it is Genuine ETRG release @ ExtraTorrent.cc or from our Trusted Accounts elswhere","torrent":{"xt":"urn:btih:a83bc1a1016163011219df23377b6de06f77ed5f","amp;dn":"Showdown.in.Manila.2016.1080p.WEBRip.AAC.x264-ETRG","amp;tr":["udp%3A%2F%2Ftracker.leechers-paradise.org%3A6969","udp%3A%2F%2Fzer0day.ch%3A1337","udp%3A%2F%2Fopen.demonii.com%3A1337","udp%3A%2F%2Ftracker.coppersurfer.tk%3A6969","udp%3A%2F%2Fexodus.desync.com%3A6969"],"infoHash":"a83bc1a1016163011219df23377b6de06f77ed5f","infoHashBuffer":{"type":"Buffer","data":[168,59,193,161,1,97,99,1,18,25,223,35,55,123,109,224,111,119,237,95]},"announce":[],"urlList":[]}}