{"title":"Soilless Gardening","uid":8219402,"size":32701587,"categoryP":"other","categoryS":"e_books","magnet":"?xt=urn:btih:aa5005175a33ae95e2cd4240361996c5c30f3293&amp;dn=Soilless+Gardening&amp;tr=udp%3A%2F%2Ftracker.openbittorrent.com%3A80&amp;tr=udp%3A%2F%2Fopen.demonii.com%3A1337&amp;tr=udp%3A%2F%2Ftracker.coppersurfer.tk%3A6969&amp;tr=udp%3A%2F%2Fexodus.desync.com%3A6969","seeders":5,"leechers":0,"uploader":"Survival_Library","files":1,"time":1362437648,"description":" &lt;a href=&quot;http://www.survivallibrary.me/775/gardening-permaculture-hydroponics-aquaponics/soilless-gardening/&quot; rel=&quot;nofollow&quot; target=&quot;_NEW&quot;&gt;http://www.survivallibrary.me/775/gardening-permaculture-hydroponics-aquaponics/soilless-gardening/&lt;/a&gt;\n","torrent":{"xt":"urn:btih:aa5005175a33ae95e2cd4240361996c5c30f3293","amp;dn":"Soilless+Gardening","amp;tr":["udp%3A%2F%2Ftracker.openbittorrent.com%3A80","udp%3A%2F%2Fopen.demonii.com%3A1337","udp%3A%2F%2Ftracker.coppersurfer.tk%3A6969","udp%3A%2F%2Fexodus.desync.com%3A6969"],"infoHash":"aa5005175a33ae95e2cd4240361996c5c30f3293","infoHashBuffer":{"type":"Buffer","data":[170,80,5,23,90,51,174,149,226,205,66,64,54,25,150,197,195,15,50,147]},"announce":[],"urlList":[]}}