{"title":"Life.Is.Strange.Episode.1-RELOADED","uid":11671893,"size":2321346983,"categoryP":"games","categoryS":"pc","magnet":"?xt=urn:btih:c2cc549a4c434fc20b4e9721aca398fac5942688&amp;dn=Life.Is.Strange.Episode.1-RELOADED&amp;tr=udp%3A%2F%2Ftracker.openbittorrent.com%3A80&amp;tr=udp%3A%2F%2Fopen.demonii.com%3A1337&amp;tr=udp%3A%2F%2Ftracker.coppersurfer.tk%3A6969&amp;tr=udp%3A%2F%2Fexodus.desync.com%3A6969","seeders":5,"leechers":1,"uploader":"SaNRiM","files":2,"time":1422727364,"description":"[img]http://s2.postimg.org/utbtkesqx/cover2.jpg[/img]\n\nABOUT THE GAME\n\nLife Is Strange is a five part episodic game that sets out to revolutionise story based choice and consequence games by allowing the player to rewind time and affect the past, present and future.\n\nYou are Max, a photography senior who saves her old friend Chloe by discovering she can rewind time. The pair soon find themselves exposed to the darker side of Arcadia Bay as they uncover the disturbing truth behind the sudden disappearance of a fellow student.\n\nMeanwhile, Max begins to have premonitions as she struggles to understand the implications of her power. She must quickly learn that changing the past can sometimes lead to a devastating future.\n\nFEATURES\n\nA beautifully written modern adventure game.\nRewind time to change the course of events.\nMultiple endings depending on the choices you make.\nStriking, hand-painted visuals.\nDistinct, licensed indie soundtrack.\n\nTitle: Life Is Strangeâ„¢\nGenre: Action, Adventure\nDeveloper: DONTNOD Entertainment\nPublisher: SQUARE ENIX\nRelease Date: Jan 29, 2015\n\n\n\n- Extract\n- Burn or mount the .iso\n- Run setup.exe and install\n- copy crack dir to installdir\n- Play the game\n\n\n\n[img]http://s2.postimg.org/drizibdvt/scr1.jpg[/img]\n[img]http://s23.postimg.org/imxgtaiyz/scr2.jpg[/img]\n[img]http://s23.postimg.org/5t40doux7/scr3.jpg[/img]\n[img]http://s23.postimg.org/meg873bez/scr4.jpg[/img]","torrent":{"xt":"urn:btih:c2cc549a4c434fc20b4e9721aca398fac5942688","amp;dn":"Life.Is.Strange.Episode.1-RELOADED","amp;tr":["udp%3A%2F%2Ftracker.openbittorrent.com%3A80","udp%3A%2F%2Fopen.demonii.com%3A1337","udp%3A%2F%2Ftracker.coppersurfer.tk%3A6969","udp%3A%2F%2Fexodus.desync.com%3A6969"],"infoHash":"c2cc549a4c434fc20b4e9721aca398fac5942688","infoHashBuffer":{"type":"Buffer","data":[194,204,84,154,76,67,79,194,11,78,151,33,172,163,152,250,197,148,38,136]},"announce":[],"urlList":[]}}