{"title":"Milton.Jones.Live.2013.On.The.Road.DVDRip.x264-HAGGiS","uid":9253643,"size":652540404,"categoryP":"video","categoryS":"movies","magnet":"?xt=urn:btih:cbd33c4175694a65357f3bd3c045293362732201&amp;dn=Milton.Jones.Live.2013.On.The.Road.DVDRip.x264-HAGGiS&amp;tr=udp%3A%2F%2Ftracker.openbittorrent.com%3A80&amp;tr=udp%3A%2F%2Fopen.demonii.com%3A1337&amp;tr=udp%3A%2F%2Ftracker.coppersurfer.tk%3A6969&amp;tr=udp%3A%2F%2Fexodus.desync.com%3A6969","seeders":5,"leechers":0,"uploader":"Drarbg","files":3,"time":1385510278,"description":"Milton.Jones.Live.2013.On.The.Road.DVDRip.x264-HAGGiS\n-----------------------------------------\nScreens : &lt;a href=&quot;\nhttp://imagecurl.org/viewer.php?file=60887853995844098226.jpg&quot; rel=&quot;nofollow&quot; target=&quot;_NEW&quot;&gt;\nhttp://imagecurl.org/viewer.php?file=60887853995844098226.jpg&lt;/a&gt;\n\n","torrent":{"xt":"urn:btih:cbd33c4175694a65357f3bd3c045293362732201","amp;dn":"Milton.Jones.Live.2013.On.The.Road.DVDRip.x264-HAGGiS","amp;tr":["udp%3A%2F%2Ftracker.openbittorrent.com%3A80","udp%3A%2F%2Fopen.demonii.com%3A1337","udp%3A%2F%2Ftracker.coppersurfer.tk%3A6969","udp%3A%2F%2Fexodus.desync.com%3A6969"],"infoHash":"cbd33c4175694a65357f3bd3c045293362732201","infoHashBuffer":{"type":"Buffer","data":[203,211,60,65,117,105,74,101,53,127,59,211,192,69,41,51,98,115,34,1]},"announce":[],"urlList":[]}}