{"title":"3.Days.To.Kill.2014.EXTENDED.1080p.BluRay.DTS-HD.MA.5.1.x264-Pub","uid":10105215,"size":13762321814,"categoryP":"video","categoryS":"hd___movies","magnet":"?xt=urn:btih:d203e6a78c4fc9ff6ae2014899bb29dbcc5b16cb&amp;dn=3.Days.To.Kill.2014.EXTENDED.1080p.BluRay.DTS-HD.MA.5.1.x264-Pub&amp;tr=udp%3A%2F%2Ftracker.openbittorrent.com%3A80&amp;tr=udp%3A%2F%2Fopen.demonii.com%3A1337&amp;tr=udp%3A%2F%2Ftracker.coppersurfer.tk%3A6969&amp;tr=udp%3A%2F%2Fexodus.desync.com%3A6969","seeders":5,"leechers":2,"uploader":"BOZX","files":-1,"time":1399451837,"description":"\n                PublicHD - High-Definition Bittorrent Community\n      \n              ----------------------------------------------------\n\n3.Days.To.Kill.2014.EXTENDED.1080p.BluRay.DTS-HD.MA.5.1.x264-PublicHD\n\n &lt;a href=&quot; http://www.imdb.com/title/tt2172934/&quot; rel=&quot;nofollow&quot; target=&quot;_NEW&quot;&gt; http://www.imdb.com/title/tt2172934/&lt;/a&gt;\n\nRating .............: 6.3/10 from 6,650 users  \nScreens.............: $12,242,218 (USA) (23 February 2014) (2,872 Screens)\nGenre ..............: Action | Crime | Drama | Thriller\n   \nDate ...............: May 7 2014\nRuntime ............: 2hr 2m\nSize ...............: 12.8 GB\nVideo ..............: 1920x808\nBitrate ............: 10792 kbps (x264 &lt;a class=&quot;__cf_email__&quot; href=&quot;/cdn-cgi/l/email-protection&quot; data-cfemail=&quot;eca4858b84aca0d8c2dd&quot;&gt;[email&amp;#160;protected]&lt;/a&gt;&lt;script cf-hash='f9e31' type=&quot;text/javascript&quot;&gt;\n/* &lt;![CDATA[ */!function(){try{var t=&quot;currentScript&quot;in document?document.currentScript:function(){for(var t=document.getElementsByTagName(&quot;script&quot;),e=t.length;e--;)if(t[e].getAttribute(&quot;cf-hash&quot;))return t[e]}();if(t&amp;&amp;t.previousSibling){var e,r,n,i,c=t.previousSibling,a=c.getAttribute(&quot;data-cfemail&quot;);if(a){for(e=&quot;&quot;,r=parseInt(a.substr(0,2),16),n=2;a.length-n;n+=2)i=parseInt(a.substr(n,2),16)^r,e+=String.fromCharCode(i);e=document.createTextNode(e),c.parentNode.replaceChild(e,c)}}}catch(u){}}();/* ]]&gt; */&lt;/script&gt;)\nAudio 1.............: English DTS-HD MA 5.1 Ch 4184 kbps\nChapters............: Yes\nSource .............: 1080p.BluRay.AVC.DTS-HD.MA.5.1-PublicHD\nSubs ...............: English Spanish\n\nS C R E E N S :\n &lt;a href=&quot;\nhttp://istoreimg.com/i/5369d3355dfa3.html&quot; rel=&quot;nofollow&quot; target=&quot;_NEW&quot;&gt;\nhttp://istoreimg.com/i/5369d3355dfa3.html&lt;/a&gt; \n &lt;a href=&quot;\nhttp://istoreimg.com/i/5369d3369ec69.html&quot; rel=&quot;nofollow&quot; target=&quot;_NEW&quot;&gt;\nhttp://istoreimg.com/i/5369d3369ec69.html&lt;/a&gt; \n &lt;a href=&quot;\nhttp://istoreimg.com/i/5369d337cfef4.html&quot; rel=&quot;nofollow&quot; target=&quot;_NEW&quot;&gt;\nhttp://istoreimg.com/i/5369d337cfef4.html&lt;/a&gt; \n &lt;a href=&quot;\nhttp://istoreimg.com/i/5369d338e1bdf.html&quot; rel=&quot;nofollow&quot; target=&quot;_NEW&quot;&gt;\nhttp://istoreimg.com/i/5369d338e1bdf.html&lt;/a&gt; \n\n\n\n\n\n\n\n","torrent":{"xt":"urn:btih:d203e6a78c4fc9ff6ae2014899bb29dbcc5b16cb","amp;dn":"3.Days.To.Kill.2014.EXTENDED.1080p.BluRay.DTS-HD.MA.5.1.x264-Pub","amp;tr":["udp%3A%2F%2Ftracker.openbittorrent.com%3A80","udp%3A%2F%2Fopen.demonii.com%3A1337","udp%3A%2F%2Ftracker.coppersurfer.tk%3A6969","udp%3A%2F%2Fexodus.desync.com%3A6969"],"infoHash":"d203e6a78c4fc9ff6ae2014899bb29dbcc5b16cb","infoHashBuffer":{"type":"Buffer","data":[210,3,230,167,140,79,201,255,106,226,1,72,153,187,41,219,204,91,22,203]},"announce":[],"urlList":[]}}