{"title":"WWE Greatest Stars of the 90s 2009 720p WEBRip h264-WD","uid":12143370,"size":4538540228,"categoryP":"video","categoryS":"movies","magnet":"?xt=urn:btih:d63becda05d9575f65198091179ef8ad22c6d8d2&amp;dn=WWE+Greatest+Stars+of+the+90s+2009+720p+WEBRip+h264-WD&amp;tr=udp%3A%2F%2Ftracker.openbittorrent.com%3A80&amp;tr=udp%3A%2F%2Fopen.demonii.com%3A1337&amp;tr=udp%3A%2F%2Ftracker.coppersurfer.tk%3A6969&amp;tr=udp%3A%2F%2Fexodus.desync.com%3A6969","seeders":5,"leechers":1,"uploader":"Lil_Jimmy1999","files":3,"time":1437403409,"description":"Witness 15 of the greatest stars of a turbulent era in which WWE and WCW battled for dominance of the sports-entertainment industry. \n\nEvent: WWE.Greatest.Stars.of.the.90s.2009.720p.WEBRip.h264-WD \nReleased: 2015.07.17 \nSource: WWE Network \nResolution: 1280 x 720 @ 29.970 FPS \nVideo: x264 @ 4500 kbps \nAudio: AAC @ 96 kbps \nSize: 4.22 GB \nRuntime: 2h 14mn \n\nWD: The Original \nHEEL \n\nUntouched/remuxed video stream from the WWE Network. \n\nAs of July 13th, we're changing our formatting to better reflect our sources","torrent":{"xt":"urn:btih:d63becda05d9575f65198091179ef8ad22c6d8d2","amp;dn":"WWE+Greatest+Stars+of+the+90s+2009+720p+WEBRip+h264-WD","amp;tr":["udp%3A%2F%2Ftracker.openbittorrent.com%3A80","udp%3A%2F%2Fopen.demonii.com%3A1337","udp%3A%2F%2Ftracker.coppersurfer.tk%3A6969","udp%3A%2F%2Fexodus.desync.com%3A6969"],"infoHash":"d63becda05d9575f65198091179ef8ad22c6d8d2","infoHashBuffer":{"type":"Buffer","data":[214,59,236,218,5,217,87,95,101,25,128,145,23,158,248,173,34,198,216,210]},"announce":[],"urlList":[]}}