{"title":"J. D. Jackson, Classical Electrodynamics, 3rd ed. (pdf)","uid":8005284,"size":88392589,"categoryP":"other","categoryS":"e_books","magnet":"?xt=urn:btih:db7ab00b71d610f85765d18c6e1db90f9271b5ba&amp;dn=J.+D.+Jackson%2C+Classical+Electrodynamics%2C+3rd+ed.+%28pdf%29&amp;tr=udp%3A%2F%2Ftracker.openbittorrent.com%3A80&amp;tr=udp%3A%2F%2Fopen.demonii.com%3A1337&amp;tr=udp%3A%2F%2Ftracker.coppersurfer.tk%3A6969&amp;tr=udp%3A%2F%2Fexodus.desync.com%3A6969","seeders":5,"leechers":0,"uploader":"zzxjoanw","files":1,"time":1357872034,"description":"Publication Date: August 10, 1998 | ISBN-10: 047130932X | ISBN-13: 978-0471309321 | Edition: 3","torrent":{"xt":"urn:btih:db7ab00b71d610f85765d18c6e1db90f9271b5ba","amp;dn":"J.+D.+Jackson%2C+Classical+Electrodynamics%2C+3rd+ed.+%28pdf%29","amp;tr":["udp%3A%2F%2Ftracker.openbittorrent.com%3A80","udp%3A%2F%2Fopen.demonii.com%3A1337","udp%3A%2F%2Ftracker.coppersurfer.tk%3A6969","udp%3A%2F%2Fexodus.desync.com%3A6969"],"infoHash":"db7ab00b71d610f85765d18c6e1db90f9271b5ba","infoHashBuffer":{"type":"Buffer","data":[219,122,176,11,113,214,16,248,87,101,209,140,110,29,185,15,146,113,181,186]},"announce":[],"urlList":[]}}