{"title":"The.Best.of.Youth.2003.720p.WEB-DL.H264-HULU [PublicHD]","uid":8504714,"size":8696267494,"categoryP":"video","categoryS":"hd___movies","magnet":"?xt=urn:btih:dfed61446f1c352447f9059643fe766645221ac0&amp;dn=The.Best.of.Youth.2003.720p.WEB-DL.H264-HULU+%5BPublicHD%5D&amp;tr=udp%3A%2F%2Ftracker.openbittorrent.com%3A80&amp;tr=udp%3A%2F%2Fopen.demonii.com%3A1337&amp;tr=udp%3A%2F%2Ftracker.coppersurfer.tk%3A6969&amp;tr=udp%3A%2F%2Fexodus.desync.com%3A6969","seeders":5,"leechers":2,"uploader":"aoloffline","files":2,"time":1369396255,"description":"                PublicHD - High-Definition Bittorrent Community\n      \n                           &lt;a href=&quot; https://publichd.se/&quot; rel=&quot;nofollow&quot; target=&quot;_NEW&quot;&gt; https://publichd.se/&lt;/a&gt;\n    \n              ----------------------------------------------------\n\nThe.Best.of.Youth.2003.720p.WEB-DL.H264-HULU [PublicHD]\n &lt;a href=&quot;\nhttp://www.imdb.com/title/tt0346336&quot; rel=&quot;nofollow&quot; target=&quot;_NEW&quot;&gt;\nhttp://www.imdb.com/title/tt0346336&lt;/a&gt;\n\nLength............: 6:07:00\nVideo.............: H264 @ 3000 kbps (1280x720)\nFPS...............: 23.976\nAudio.............: Italian AAC 2.0 Ch\nSubs..............: English Hard Coded\n\n\nSCREENS\n &lt;a href=&quot;\nhttp://i.imgbox.com/abbdcE5q.png&quot; rel=&quot;nofollow&quot; target=&quot;_NEW&quot;&gt;\nhttp://i.imgbox.com/abbdcE5q.png&lt;/a&gt;\n &lt;a href=&quot;\nhttp://i.imgbox.com/aczPwT7Q.png&quot; rel=&quot;nofollow&quot; target=&quot;_NEW&quot;&gt;\nhttp://i.imgbox.com/aczPwT7Q.png&lt;/a&gt;\n &lt;a href=&quot;\nhttp://i.imgbox.com/abnxVyje.png&quot; rel=&quot;nofollow&quot; target=&quot;_NEW&quot;&gt;\nhttp://i.imgbox.com/abnxVyje.png&lt;/a&gt;\n &lt;a href=&quot;\nhttp://i.imgbox.com/abmrunrZ.png&quot; rel=&quot;nofollow&quot; target=&quot;_NEW&quot;&gt;\nhttp://i.imgbox.com/abmrunrZ.png&lt;/a&gt;\n &lt;a href=&quot;\nhttp://i.imgbox.com/abi9jVDv.png&quot; rel=&quot;nofollow&quot; target=&quot;_NEW&quot;&gt;\nhttp://i.imgbox.com/abi9jVDv.png&lt;/a&gt;\n &lt;a href=&quot;\nhttp://i.imgbox.com/abknoVfM.png&quot; rel=&quot;nofollow&quot; target=&quot;_NEW&quot;&gt;\nhttp://i.imgbox.com/abknoVfM.png&lt;/a&gt;\n","torrent":{"xt":"urn:btih:dfed61446f1c352447f9059643fe766645221ac0","amp;dn":"The.Best.of.Youth.2003.720p.WEB-DL.H264-HULU+%5BPublicHD%5D","amp;tr":["udp%3A%2F%2Ftracker.openbittorrent.com%3A80","udp%3A%2F%2Fopen.demonii.com%3A1337","udp%3A%2F%2Ftracker.coppersurfer.tk%3A6969","udp%3A%2F%2Fexodus.desync.com%3A6969"],"infoHash":"dfed61446f1c352447f9059643fe766645221ac0","infoHashBuffer":{"type":"Buffer","data":[223,237,97,68,111,28,53,36,71,249,5,150,67,254,118,102,69,34,26,192]},"announce":[],"urlList":[]}}