{"title":"The.Big.Bang.Theory.S05E22.FASTSUB.VOSTFR.HDTV.XviD-F4ST","uid":7221576,"size":182799684,"categoryP":"video","categoryS":"tv_shows","magnet":"?xt=urn:btih:e1924ae820b79f8da0fb060a349dd3d33600eb0f&amp;dn=The.Big.Bang.Theory.S05E22.FASTSUB.VOSTFR.HDTV.XviD-F4ST&amp;tr=udp%3A%2F%2Ftracker.openbittorrent.com%3A80&amp;tr=udp%3A%2F%2Fopen.demonii.com%3A1337&amp;tr=udp%3A%2F%2Ftracker.coppersurfer.tk%3A6969&amp;tr=udp%3A%2F%2Fexodus.desync.com%3A6969","seeders":5,"leechers":0,"uploader":"maximersk","files":1,"time":1335543714,"description":"The.Big.Bang.Theory.S05E22.FASTSUB.VOSTFR.HDTV.XviD-F4ST","torrent":{"xt":"urn:btih:e1924ae820b79f8da0fb060a349dd3d33600eb0f","amp;dn":"The.Big.Bang.Theory.S05E22.FASTSUB.VOSTFR.HDTV.XviD-F4ST","amp;tr":["udp%3A%2F%2Ftracker.openbittorrent.com%3A80","udp%3A%2F%2Fopen.demonii.com%3A1337","udp%3A%2F%2Ftracker.coppersurfer.tk%3A6969","udp%3A%2F%2Fexodus.desync.com%3A6969"],"infoHash":"e1924ae820b79f8da0fb060a349dd3d33600eb0f","infoHashBuffer":{"type":"Buffer","data":[225,146,74,232,32,183,159,141,160,251,6,10,52,157,211,211,54,0,235,15]},"announce":[],"urlList":[]}}