{"title":"Jojo Moyes: 9 Novels - Kindle + ePub - Barbie 1710","uid":8105860,"size":10466724,"categoryP":"other","categoryS":"e_books","magnet":"?xt=urn:btih:f681f2eafaae942b4126feb6d13d3eff8cad9248&amp;dn=Jojo+Moyes%3A+9+Novels+-+Kindle+%2B+ePub+-+Barbie+1710&amp;tr=udp%3A%2F%2Ftracker.openbittorrent.com%3A80&amp;tr=udp%3A%2F%2Fopen.demonii.com%3A1337&amp;tr=udp%3A%2F%2Ftracker.coppersurfer.tk%3A6969&amp;tr=udp%3A%2F%2Fexodus.desync.com%3A6969","seeders":5,"leechers":0,"uploader":"Barbie1710","files":39,"time":1360080425,"description":"Jojo Moyes: 9 Novels - Kindle + ePub\n\nPeacock Emporium\nShip of Brides\nNight Music\nSilver Bay\nThe Horse Dancer\nThe Last Letter From Your Lover\nMe Before You\nHoneymoon in Paris: A Novella\nThe Girl You Left Behind\n\nThis is a multi-tracker torrent.  Please check your Bit-Torrent client for the true number of seeds.  Enjoy &amp; Please Seed","torrent":{"xt":"urn:btih:f681f2eafaae942b4126feb6d13d3eff8cad9248","amp;dn":"Jojo+Moyes%3A+9+Novels+-+Kindle+%2B+ePub+-+Barbie+1710","amp;tr":["udp%3A%2F%2Ftracker.openbittorrent.com%3A80","udp%3A%2F%2Fopen.demonii.com%3A1337","udp%3A%2F%2Ftracker.coppersurfer.tk%3A6969","udp%3A%2F%2Fexodus.desync.com%3A6969"],"infoHash":"f681f2eafaae942b4126feb6d13d3eff8cad9248","infoHashBuffer":{"type":"Buffer","data":[246,129,242,234,250,174,148,43,65,38,254,182,209,61,62,255,140,173,146,72]},"announce":[],"urlList":[]}}